pyavevae3dext/__init__.py
pyavevae3dext/pyavevae3dext.pyd
pyavevae3dext-0.0.2.dist-info/LICENSE
pyavevae3dext-0.0.2.dist-info/METADATA
pyavevae3dext-0.0.2.dist-info/WHEEL
pyavevae3dext-0.0.2.dist-info/top_level.txt
pyavevae3dext-0.0.2.dist-info/RECORD
