Metadata-Version: 2.1
Name: pyavevae3dext
Version: 0.0.2
Summary: Python Package Allows to interact with AVEVA E3D2.1.0.3 using AVEVA Embadded Python Interaction dll..
Home-page: https://github.com/shivangKheradiya/PyAVEVAE3D
Author: Shivang Kheradiya
Author-email: shivangatul@gmail.com
License: MIT license
Project-URL: Documentation, https://github.com/shivangKheradiya/PyAVEVAE3D
Project-URL: Source, https://github.com/shivangKheradiya/PyAVEVAE3D
Classifier: Programming Language :: Python :: 3.10
Classifier: Programming Language :: Python :: Implementation :: CPython
Classifier: Topic :: Software Development :: Libraries
Classifier: Topic :: Utilities
Requires-Python: >=3.10,<3.11
License-File: LICENSE
